aidev/__init__.py
aidev/aidev.py
aidev/blocks/__init__.py
aidev/blocks/data.py
aidev/blocks/optimization.py
aidev/blocks/postprocessing.py
aidev/blocks/sampling.py
aidev/blocks/surrogates.py
aidev/interfaces/__init__.py
aidev/interfaces/nx_interface.py
aidev/utilities/__init__.py
aidev/utilities/types.py
aidev-1.2.dist-info/LICENSE
aidev-1.2.dist-info/METADATA
aidev-1.2.dist-info/WHEEL
aidev-1.2.dist-info/top_level.txt
aidev-1.2.dist-info/RECORD
